<?xml version="1.0" encoding="utf-8"?><HelpTOCNode Title="ICacheListener Methods" Url="html/D5369F6E.htm"><HelpTOCNode Title="AfterCreate Method " Url="html/BF2F0E7B.htm" /><HelpTOCNode Title="AfterDestroy Method " Url="html/368D62D9.htm" /><HelpTOCNode Title="AfterInvalidate Method " Url="html/5A16A564.htm" /><HelpTOCNode Title="AfterRegionClear Method " Url="html/9FAD060E.htm" /><HelpTOCNode Title="AfterRegionDestroy Method " Url="html/CE7B4535.htm" /><HelpTOCNode Title="AfterRegionDisconnected Method " Url="html/33F57A36.htm" /><HelpTOCNode Title="AfterRegionInvalidate Method " Url="html/1E2FCE84.htm" /><HelpTOCNode Title="AfterRegionLive Method " Url="html/6975A2FD.htm" /><HelpTOCNode Title="AfterUpdate Method " Url="html/205E88EC.htm" /><HelpTOCNode Title="Close Method " Url="html/DF117689.htm" /></HelpTOCNode>